tfc_admin/__init__.py
tfc_admin/__main__.py
tfc_admin-1.1.0.dist-info/METADATA
tfc_admin-1.1.0.dist-info/WHEEL
tfc_admin-1.1.0.dist-info/RECORD
